octobot_pro/__init__.py
octobot_pro/cli.py
octobot_pro/constants.py
octobot_pro/api/__init__.py
octobot_pro/api/data_fetching.py
octobot_pro/api/execution.py
octobot_pro/api/ploting.py
octobot_pro/internal/__init__.py
octobot_pro/internal/backtester_trading_mode.py
octobot_pro/internal/logging_util.py
octobot_pro/internal/octobot_mocks.py
octobot_pro/internal/runners.py
octobot_pro/model/__init__.py
octobot_pro/model/backtest_plot.py
octobot_pro/model/backtest_result.py
octobot_pro/model/errors.py
octobot_pro/model/strategy.py
octobot_pro/resources/__init__.py
tests/api/__init__.py
tests/api/test_data_fetching.py
tests/api/test_execution.py
tests/functionnal/__init__.py
tests/functionnal/example_scripts/__init__.py
tests/functionnal/example_scripts/test_precomputed_vs_iteration_rsi.py
OctoBot_Pro-0.0.1.dist-info/LICENSE
OctoBot_Pro-0.0.1.dist-info/METADATA
OctoBot_Pro-0.0.1.dist-info/WHEEL
OctoBot_Pro-0.0.1.dist-info/entry_points.txt
OctoBot_Pro-0.0.1.dist-info/top_level.txt
OctoBot_Pro-0.0.1.dist-info/RECORD
