Metadata-Version: 2.1
Name: OctoBot-Pro
Version: 0.0.1
Summary: Backtesting framework of the OctoBot Ecosystem
Home-page: https://github.com/Drakkar-Software/OctoBot-Pro
Author: Drakkar-Software
Author-email: drakkar-software@protonmail.com
License: GPL-3.0
Classifier: Development Status :: 5 - Production/Stable
Classifier: Operating System :: OS Independent
Classifier: Operating System :: MacOS :: MacOS X
Classifier: Operating System :: Microsoft :: Windows
Classifier: Operating System :: POSIX
Classifier: Programming Language :: Python :: 3.8
Classifier: Programming Language :: Python :: 3.9
Requires-Python: >=3.8
License-File: LICENSE
Requires-Dist: OctoBot (==0.4.31)
Requires-Dist: appdirs (==1.4.4)
Requires-Dist: click (==8.1.3)
Requires-Dist: jinja2
Requires-Dist: aiohttp
